arso2weather/__init__.py
arso2weather/main.py
arso2weather-1.0.1.dist-info/METADATA
arso2weather-1.0.1.dist-info/WHEEL
arso2weather-1.0.1.dist-info/top_level.txt
arso2weather-1.0.1.dist-info/RECORD
