Metadata-Version: 2.1
Name: arso2weather
Version: 1.0.1
Summary: Basic package to get the current temperature of Slovenians cities.
Home-page: https://github.com/svenko99/arso2weather
Author: Sven Ulcar
Author-email: <sven.ulcar@gmail.com>
Keywords: python,weather,slovenia,arso,vreme
Classifier: Intended Audience :: Developers
Classifier: Programming Language :: Python :: 3
Classifier: Operating System :: Unix
Classifier: Operating System :: MacOS :: MacOS X
Requires-Dist: requests
